cli/__init__.py
cli/main.py
openmailercli-0.1.3.dist-info/LICENSE
openmailercli-0.1.3.dist-info/METADATA
openmailercli-0.1.3.dist-info/WHEEL
openmailercli-0.1.3.dist-info/entry_points.txt
openmailercli-0.1.3.dist-info/top_level.txt
openmailercli-0.1.3.dist-info/RECORD
