Metadata-Version: 2.1
Name: openmailercli
Version: 0.1.3
Summary: A pure Python open-source email delivery tool
Author: Mohamed Sesay
Classifier: Programming Language :: Python :: 3
Classifier: License :: OSI Approved :: MIT License
Classifier: Operating System :: OS Independent
Requires-Python: >=3.7
License-File: LICENSE
Requires-Dist: click >=8.0.0
Requires-Dist: jinja2 >=3.0.0
Requires-Dist: openmailer
Requires-Dist: openmailer >=0.1.1
Requires-Dist: python-dotenv >=1.0.0
Requires-Dist: pyyaml >=6.0.0
Requires-Dist: requests >=2.0.0
Requires-Dist: rich >=13.0.0
